odoo/addons/product_pricelist_by_contact/README.rst
odoo/addons/product_pricelist_by_contact/__init__.py
odoo/addons/product_pricelist_by_contact/__manifest__.py
odoo/addons/product_pricelist_by_contact/i18n/it.po
odoo/addons/product_pricelist_by_contact/i18n/product_pricelist_by_contact.pot
odoo/addons/product_pricelist_by_contact/readme/CONTRIBUTORS.rst
odoo/addons/product_pricelist_by_contact/readme/DESCRIPTION.rst
odoo/addons/product_pricelist_by_contact/readme/ROADMAP.rst
odoo/addons/product_pricelist_by_contact/readme/USAGE.rst
odoo/addons/product_pricelist_by_contact/static/description/icon.png
odoo/addons/product_pricelist_by_contact/static/description/index.html
odoo/addons/product_pricelist_by_contact/views/res_partner_views.xml
odoo13_addon_product_pricelist_by_contact-13.0.1.0.1.dev3.dist-info/METADATA
odoo13_addon_product_pricelist_by_contact-13.0.1.0.1.dev3.dist-info/WHEEL
odoo13_addon_product_pricelist_by_contact-13.0.1.0.1.dev3.dist-info/top_level.txt
odoo13_addon_product_pricelist_by_contact-13.0.1.0.1.dev3.dist-info/RECORD
